tbtp/__init__.py
tbtp/test.py
tbtp-0.13.dist-info/METADATA
tbtp-0.13.dist-info/RECORD
tbtp-0.13.dist-info/WHEEL
tbtp-0.13.dist-info/top_level.txt
