Metadata-Version: 2.1
Name: tbtp
Version: 0.13
Summary: Thinact BackTest Platform
Home-page: https://github.com/grantfang/tbtp
Author: Grant Fang
Author-email: grant.fang@thinact.com
License: MIT
Platform: UNKNOWN
